fir_api_cli/__init__.py
fir_api_cli/__main__.py
fir_api_cli/cli.py
fir_api_cli/config.py
fir_api_cli/constants.py
fir_api_cli/fir.py
fir_api_cli/utils.py
fir_api_cli-0.4.4.dist-info/LICENSE
fir_api_cli-0.4.4.dist-info/METADATA
fir_api_cli-0.4.4.dist-info/WHEEL
fir_api_cli-0.4.4.dist-info/entry_points.txt
fir_api_cli-0.4.4.dist-info/top_level.txt
fir_api_cli-0.4.4.dist-info/RECORD
