Metadata-Version: 2.1
Name: fir-api-cli
Version: 0.4.4
Summary: Package for exploring and downloading data from the FIR API service.
Author-email: "Earth Observation Operation Center (FOK)" <fok@lechnerkozpont.hu>
Classifier: Programming Language :: Python :: 3
Classifier: License :: OSI Approved :: MIT License
Classifier: Operating System :: OS Independent
Requires-Python: >=3.8
License-File: LICENSE
Requires-Dist: typer[all] (>=0.7.0)
Requires-Dist: requests (>=2.28.1)
Requires-Dist: requests-toolbelt (>=0.10.1)
Requires-Dist: tqdm (>=4.65.0)
Requires-Dist: gql (>=3.4.0)
